wechatf/__init__.py
wechatf/wechatf_auto_chat.py
wechatf/wechatf_http_server.py
wechatf/wechatf_http_server_start.py
wechatf/core/__init__.py
wechatf/core/conf.py
wechatf/core/deal_recv_friend_list.py
wechatf/core/frida_js.py
wechatf/core/frida_session.py
wechatf/core/js/v3_2_1_154_x86/get_login_user_info.js
wechatf/core/js/v3_2_1_154_x86/goto_login_qrcode.js
wechatf/core/js/v3_2_1_154_x86/is_login.js
wechatf/core/js/v3_2_1_154_x86/logout.js
wechatf/core/js/v3_2_1_154_x86/recv_friend_list.js
wechatf/core/js/v3_2_1_154_x86/recv_login_qrcode.js
wechatf/core/js/v3_2_1_154_x86/recv_message.js
wechatf/core/js/v3_2_1_154_x86/recv_message.md
wechatf/core/js/v3_2_1_154_x86/send_message.js
wechatf/core/js/v3_2_1_154_x86/send_message.md
wechatf/core/js/v3_9_5_80_x86/recv_message.js
wechatf/core/js/v3_9_5_80_x86/recv_message.md
wechatf/core/js/v3_9_5_80_x86/send_message.js
wechatf/core/js/v3_9_5_80_x86/send_message.md
wechatf-0.0.3.dist-info/LICENSE
wechatf-0.0.3.dist-info/METADATA
wechatf-0.0.3.dist-info/WHEEL
wechatf-0.0.3.dist-info/entry_points.txt
wechatf-0.0.3.dist-info/top_level.txt
wechatf-0.0.3.dist-info/RECORD
