Metadata-Version: 2.1
Name: wechatf
Version: 0.0.3
Summary: wechatf 微信机器人框架（自动聊天、http协议访问）。
Home-page: https://github.com/luoyeah/wechat-frida
Author: luoyeah
Author-email: dao696@foxmail.com
Maintainer: 
Maintainer-email: 
License: MIT license
Platform: Windows
Classifier: Programming Language :: Python :: 3.8
Classifier: Programming Language :: Python :: Implementation :: CPython
Requires-Dist: frida (==16.0.19)
Requires-Dist: openai (==0.27.8)
Requires-Dist: fastapi (==0.97.0)
Requires-Dist: uvicorn (==0.22.0)
Requires-Dist: pywin32 (==306)
Requires-Dist: pefile (==2023.2.7)
